README.md
setup.cfg
setup.py
olyn.egg-info/PKG-INFO
olyn.egg-info/SOURCES.txt
olyn.egg-info/dependency_links.txt
olyn.egg-info/not-zip-safe
olyn.egg-info/requires.txt
olyn.egg-info/top_level.txt
src/__init__.py
src/olyn/__init__.py
src/olyn/api.py
src/olyn/assets.py
src/olyn/errors.py
src/olyn/utils.py
src/olyn/version.py