Metadata-Version: 2.1
Name: olyn
Version: 0.0.3.post0
Summary: Python client library for the Olyn API
Home-page: https://github.com/Olyn-inc/olyn-sdk-python
Download-URL: https://github.com/Olyn-inc/olyn-sdk-python/tarball/v0.0.3r
Author: Olyn, inc
Author-email: dev@olyn.com
License: MIT
Keywords: api client olyn token web3 blockchain asset registry
Classifier: Development Status :: 4 - Beta
Classifier: Intended Audience :: Developers
Classifier: License :: OSI Approved :: MIT License
Classifier: Operating System :: OS Independent
Classifier: Programming Language :: Python
Classifier: Programming Language :: Python :: 3.4
Classifier: Programming Language :: Python :: 3.5
Classifier: Programming Language :: Python :: 3.6
Classifier: Programming Language :: Python :: 3.7
Classifier: Programming Language :: Python :: 3.8
Classifier: Programming Language :: Python :: 3.9
Classifier: Programming Language :: Python :: 3.10
Classifier: Programming Language :: Python :: Implementation :: PyPy
Classifier: Topic :: Software Development :: Libraries :: Python Modules
Requires-Python: >=3.4
